geepers/__init__.py
geepers/_types.py
geepers/_version.py
geepers/analysis.py
geepers/cli.py
geepers/constants.py
geepers/gps.py
geepers/io.py
geepers/midas.py
geepers/plotting.py
geepers/processing.py
geepers/py.typed
geepers/quality.py
geepers/rates.py
geepers/schemas.py
geepers/uncertainty.py
geepers/utils.py
geepers/workflows.py
geepers/gps_sources/__init__.py
geepers/gps_sources/base.py
geepers/gps_sources/sideshow.py
geepers/gps_sources/unr.py
geepers/gps_sources/unr_grid.py
geepers-0.3.0.dist-info/licenses/LICENSE
geepers-0.3.0.dist-info/METADATA
geepers-0.3.0.dist-info/WHEEL
geepers-0.3.0.dist-info/entry_points.txt
geepers-0.3.0.dist-info/top_level.txt
geepers-0.3.0.dist-info/RECORD
