Metadata-Version: 2.4
Name: geepers
Version: 0.3.0
Summary: Download GPS data and compare to InSAR
Author-email: Scott Staniewicz <scott.j.staniewicz@jpl.nasa.gov>
Project-URL: Homepage, https://github.com/isce-framework/geepers
Project-URL: Bug Tracker, https://github.com/isce-framework/geepers/issues
Project-URL: Discussions, https://github.com/isce-framework/geepers/discussions
Project-URL: Changelog, https://github.com/isce-framework/geepers/releases
Classifier: Intended Audience :: Developers
Classifier: Intended Audience :: Science/Research
Classifier: Programming Language :: Python :: 3
Classifier: Programming Language :: Python :: 3.11
Classifier: Programming Language :: Python :: 3.12
Classifier: Programming Language :: Python :: 3.13
Classifier: Programming Language :: Python
Classifier: Topic :: Scientific/Engineering
Classifier: Typing :: Typed
Requires-Python: >=3.11
License-File: LICENSE
Requires-Dist: pandas
Requires-Dist: lxml
Requires-Dist: geopandas
Requires-Dist: pyogrio
Requires-Dist: xarray
Requires-Dist: dask>=2025
Requires-Dist: pyproj
Requires-Dist: rasterio
Requires-Dist: rioxarray
Requires-Dist: shapely>=2
Requires-Dist: requests
Requires-Dist: tqdm
Requires-Dist: zarr
Requires-Dist: tyro>=0.9.24
Requires-Dist: pandera
Dynamic: license-file
